{
    "consultas": [
        {
            "name": "Marco",
            "email": "marco@gmail.com",
            "animal": "Max",
            "local": "Clinica",
            "data": "10/06/2023",
            "hora": "10:30",
            "descricao": "Consulta de rotina."
        },
        {
            "name": "Jo\u00e3o",
            "email": "joao@gmail.com",
            "animal": "Luna",
            "local": "Casa",
            "data": "21/06/2023",
            "hora": "17:30",
            "descricao": "Vacina\u00e7\u00e3o anual e exame de rotina."
        }
    ]
}